MANIFEST.in
README.md
setup.py
MetaPetzAI/__init__.py
MetaPetzAI/__main__.py
MetaPetzAI.egg-info/PKG-INFO
MetaPetzAI.egg-info/SOURCES.txt
MetaPetzAI.egg-info/dependency_links.txt
MetaPetzAI.egg-info/requires.txt
MetaPetzAI.egg-info/top_level.txt