Metadata-Version: 2.1
Name: MetaPetzAI
Version: 42.0.0.1
Summary: talk to your MetaPet
Home-page: UNKNOWN
Author: Jordan Sweetman
License: UNKNOWN
Platform: UNKNOWN
Classifier: Programming Language :: Python :: 3
Classifier: License :: OSI Approved :: MIT License
Classifier: Operating System :: OS Independent
Requires-Python: >=3.6
